gdrest/__main__.py
gdrest/main.py
levels/interact.py
levels/level.py
levels/routes.py
me/message.py
me/routes.py
songs/routes.py
songs/song.py
users/routes.py
users/search.py
users/user.py
GDRest-1.0.0.dist-info/LICENSE
GDRest-1.0.0.dist-info/METADATA
GDRest-1.0.0.dist-info/WHEEL
GDRest-1.0.0.dist-info/entry_points.txt
GDRest-1.0.0.dist-info/top_level.txt
GDRest-1.0.0.dist-info/RECORD
